gpsd_client_async/__init__.py
gpsd_client_async/client.py
gpsd_client_async/messages.py
gpsd_client_async-2.0.0.dist-info/licenses/LICENSE
gpsd_client_async-2.0.0.dist-info/METADATA
gpsd_client_async-2.0.0.dist-info/WHEEL
gpsd_client_async-2.0.0.dist-info/top_level.txt
gpsd_client_async-2.0.0.dist-info/RECORD
