Metadata-Version: 2.4
Name: gpsd-client-async
Version: 2.0.0
Summary: Read data from gpsd daemon using asyncio library
Author-email: Tomas Peterka <tomas.peterka@dronetag.com>, Zachary Juang <zachary822@me.com>
License: MIT
Classifier: Intended Audience :: Developers
Classifier: Programming Language :: Python :: 3
Requires-Python: >=3.10
License-File: LICENSE
Requires-Dist: pydantic<3.0,>=2.9.0
Dynamic: license-file
